aiogram_tests/__init__.py
aiogram_tests/exceptions.py
aiogram_tests/mocked_bot.py
aiogram_tests/requester.py
aiogram_tests/utils.py
aiogram_tests/handler/__init__.py
aiogram_tests/handler/base.py
aiogram_tests/handler/handler.py
aiogram_tests/types/__init__.py
aiogram_tests/types/dataset/__init__.py
aiogram_tests/types/dataset/base.py
aiogram_tests-1.0.3.dist-info/METADATA
aiogram_tests-1.0.3.dist-info/WHEEL
aiogram_tests-1.0.3.dist-info/top_level.txt
aiogram_tests-1.0.3.dist-info/RECORD
