Metadata-Version: 2.1
Name: aiogram_tests
Version: 1.0.3
Summary: A library for testing your bots on aiogram
Author-email: Timur <pavlov.timur556@yandex.ru>
Project-URL: Homepage, https://github.com/aiogram-tests/aiogram_tests
Classifier: Programming Language :: Python :: 3
Classifier: License :: OSI Approved :: MIT License
Classifier: Operating System :: OS Independent
